hitcount/__init__.py
hitcount/admin.py
hitcount/managers.py
hitcount/models.py
hitcount/settings.py
hitcount/signals.py
hitcount/urls.py
hitcount/utils.py
hitcount/views.py
hitcount/locale/ru/LC_MESSAGES/django.mo
hitcount/locale/ru/LC_MESSAGES/django.po
hitcount/management/__init__.py
hitcount/management/__pycache__/__init__.cpython-39.pyc
hitcount/management/commands/__init__.py
hitcount/management/commands/hitcount_cleanup.py
hitcount/management/commands/__pycache__/__init__.cpython-39.pyc
hitcount/management/commands/__pycache__/hitcount_cleanup.cpython-39.pyc
hitcount/migrations/0001_initial.py
hitcount/migrations/0002_index_ip_and_session.py
hitcount/migrations/0003_auto_20190608_1004.py
hitcount/migrations/0004_auto_20200704_0933.py
hitcount/migrations/__init__.py
hitcount/migrations/__pycache__/0001_initial.cpython-39.pyc
hitcount/migrations/__pycache__/0002_index_ip_and_session.cpython-39.pyc
hitcount/migrations/__pycache__/0003_auto_20190608_1004.cpython-39.pyc
hitcount/migrations/__pycache__/0004_auto_20200704_0933.cpython-39.pyc
hitcount/migrations/__pycache__/__init__.cpython-39.pyc
hitcount/static/hitcount/hitcount-jquery.js
hitcount/static/hitcount/jquery.postcsrf.js
hitcount/templatetags/__init__.py
hitcount/templatetags/hitcount_tags.py
hitcount/templatetags/__pycache__/__init__.cpython-39.pyc
hitcount/templatetags/__pycache__/hitcount_tags.cpython-39.pyc
django_hitcount-1.3.5.dist-info/LICENSE
django_hitcount-1.3.5.dist-info/METADATA
django_hitcount-1.3.5.dist-info/WHEEL
django_hitcount-1.3.5.dist-info/top_level.txt
django_hitcount-1.3.5.dist-info/RECORD
